kimfame/__init__.py
kimfame/__main__.py
kimfame/__version__.py
kimfame/aaa.py
kimfame/bbb.py
kimfame/ccc.py
kimfame/ddd.py
kimfame/eee.py
kimfame/kimfame.py
kimfame-0.0.29.dist-info/LICENSE
kimfame-0.0.29.dist-info/WHEEL
kimfame-0.0.29.dist-info/entry_points.txt
kimfame-0.0.29.dist-info/METADATA
kimfame-0.0.29.dist-info/RECORD
